json_ref_dict/__init__.py
json_ref_dict/exceptions.py
json_ref_dict/loader.py
json_ref_dict/materialize.py
json_ref_dict/ref_dict.py
json_ref_dict/ref_pointer.py
json_ref_dict/uri.py
json_ref_dict-0.7.2.dist-info/LICENSE.txt
json_ref_dict-0.7.2.dist-info/METADATA
json_ref_dict-0.7.2.dist-info/WHEEL
json_ref_dict-0.7.2.dist-info/top_level.txt
json_ref_dict-0.7.2.dist-info/RECORD
