Metadata-Version: 2.1
Name: json-ref-dict
Version: 0.7.2
Summary: Python dict-like object which abstracts resolution of JSONSchema references
Home-page: https://github.com/jacksmith15/json-ref-dict
Author: Jack Smith
License: MIT
Classifier: Development Status :: 3 - Alpha
Classifier: Intended Audience :: Developers
Classifier: Programming Language :: Python :: 3.6
License-File: LICENSE.txt
Requires-Dist: jsonpointer (~=2.0)
